pytikz/__init__.py
pytikz/abstract.py
pytikz/constants.py
pytikz/figure.py
pytikz/node.py
pytikz/shape.py
pytikz/vector.py
pytikz/view.py
pytikz-0.0.1.dist-info/LICENSE
pytikz-0.0.1.dist-info/METADATA
pytikz-0.0.1.dist-info/WHEEL
pytikz-0.0.1.dist-info/top_level.txt
pytikz-0.0.1.dist-info/RECORD
