Metadata-Version: 2.1
Name: pytikz
Version: 0.0.1
Summary: pytikz: generate pgf/tikz files with python
Home-page: https://github.com/pglammers/pytikz
License: UNKNOWN
Platform: UNKNOWN
Classifier: Programming Language :: Python :: 3
Classifier: License :: OSI Approved :: MIT License
Classifier: Operating System :: OS Independent
Requires-Python: >=3.6
Requires-Dist: numpy (>=1.16)
